benchmarks/__init__.py
benchmarks/api_benchmark.py
benchmarks/benchmark_runner.py
benchmarks/flexible_benchmark.py
benchmarks/kubernetes_benchmark_runner.py
benchmarks/runner.py
benchmarks/api/__init__.py
benchmarks/api/benchmark_runner.py
benchmarks/api/bypass_tester.py
benchmarks/api/curl_handler.py
benchmarks/api/custom_handler.py
benchmarks/api/gemini_handler.py
benchmarks/api/huggingface_handler.py
benchmarks/api/ollama_handler.py
benchmarks/api/openai_handler.py
benchmarks/api/response_evaluator.py
benchmarks/api/runner.py
benchmarks/api/runners.py
benchmarks/core/__init__.py
benchmarks/core/base_benchmark.py
benchmarks/core/results_handler.py
benchmarks/models/__init__.py
benchmarks/models/base_handler.py
benchmarks/models/model_handler.py
benchmarks/models/model_loader.py
benchmarks/models/handlers/__init__.py
benchmarks/models/handlers/custom_api_handler.py
benchmarks/models/handlers/gemini_handler.py
benchmarks/models/handlers/guardrail_handler.py
benchmarks/models/handlers/huggingface_handler.py
benchmarks/models/handlers/ollama_handler.py
benchmarks/models/handlers/openai_handler.py
benchmarks/prompting/__init__.py
benchmarks/prompting/prompt_generator.py
benchmarks/prompting/templates.py
benchmarks/templates/__init__.py
benchmarks/templates/advanced_jailbreak_templates.py
benchmarks/templates/benchmark_template.py
benchmarks/templates/domain_templates.py
benchmarks/templates/markov_jailbreak_generator.py
benchmarks/utils/__init__.py
benchmarks/utils/backup_manager.py
benchmarks/utils/benchmark_callbacks.py
benchmarks/utils/reporting.py
cli/__init__.py
cli/config.py
cli/core.py
cli/dependency_cli.py
cli/dependency_tool.py
cli/dravik_cli.py
cli/main.py
cli/scheduler.py
cli/scheduler_service.py
cli/agent/__init__.py
cli/agent/agent.py
cli/agent/dravik_agent.py
cli/agent/streamlit_app.py
cli/commands/__init__.py
cli/commands/adversarial_commands.py
cli/commands/benchmark.py
cli/commands/dataset.py
cli/commands/delete_dataset.py
cli/commands/evaluate.py
triksha-1.0.4.dist-info/licenses/LICENSE
triksha-1.0.4.dist-info/METADATA
triksha-1.0.4.dist-info/WHEEL
triksha-1.0.4.dist-info/entry_points.txt
triksha-1.0.4.dist-info/top_level.txt
triksha-1.0.4.dist-info/RECORD
