Metadata-Version: 2.4
Name: triksha
Version: 1.0.4
Summary: Advanced LLM Security Testing Framework
Home-page: https://github.com/triksha-ai/triksha
Author: Triksha Team
Author-email: Triksha Team <team@triksha.ai>
License-Expression: MIT
Project-URL: Homepage, https://github.com/triksha-ai/triksha
Project-URL: Documentation, https://triksha.readthedocs.io/
Project-URL: Repository, https://github.com/triksha-ai/triksha
Project-URL: Bug Tracker, https://github.com/triksha-ai/triksha/issues
Keywords: llm,security,testing,jailbreak,red-team,ai-safety
Classifier: Development Status :: 5 - Production/Stable
Classifier: Intended Audience :: Developers
Classifier: Intended Audience :: Science/Research
Classifier: Topic :: Scientific/Engineering :: Artificial Intelligence
Classifier: Topic :: Security
Classifier: Programming Language :: Python :: 3
Classifier: Programming Language :: Python :: 3.9
Classifier: Programming Language :: Python :: 3.10
Classifier: Programming Language :: Python :: 3.11
Classifier: Programming Language :: Python :: 3.12
Classifier: Operating System :: OS Independent
Requires-Python: >=3.9
License-File: LICENSE
Requires-Dist: inquirer>=2.9.0
Requires-Dist: rich>=12.0.0
Requires-Dist: psutil>=5.9.0
Requires-Dist: python-daemon>=2.3.0
Requires-Dist: torch>=1.10.0
Requires-Dist: transformers>=4.37.0
Requires-Dist: datasets>=2.0.0
Requires-Dist: accelerate>=0.20.0
Requires-Dist: peft>=0.7.0
Requires-Dist: bitsandbytes>=0.41.0
Requires-Dist: evaluate>=0.4.0
Requires-Dist: sentencepiece>=0.1.99
Requires-Dist: tiktoken>=0.5.0
Requires-Dist: llama-cpp-python
Requires-Dist: sqlalchemy>=1.4.0
Requires-Dist: lancedb>=0.3.0
Requires-Dist: tqdm>=4.62.0
Requires-Dist: pydantic>=1.9.0
Requires-Dist: matplotlib>=3.5.0
Requires-Dist: openai>=1.0.0
Requires-Dist: tenacity>=8.0.0
Requires-Dist: google-generativeai>=0.3.0
Requires-Dist: backoff>=2.0.0
Requires-Dist: python-dotenv>=1.0.0
Requires-Dist: pytest>=7.0.0
Requires-Dist: pandas>=1.5.0
Provides-Extra: dev
Requires-Dist: pytest>=7.0.0; extra == "dev"
Requires-Dist: pytest-asyncio>=0.21.0; extra == "dev"
Requires-Dist: black>=22.0.0; extra == "dev"
Requires-Dist: flake8>=4.0.0; extra == "dev"
Requires-Dist: mypy>=0.991; extra == "dev"
Provides-Extra: kubernetes
Requires-Dist: kubernetes>=24.0.0; extra == "kubernetes"
Provides-Extra: web
Requires-Dist: django>=4.0.0; extra == "web"
Requires-Dist: django-rest-framework>=3.14.0; extra == "web"
Provides-Extra: all
Requires-Dist: pytest>=7.0.0; extra == "all"
Requires-Dist: pytest-asyncio>=0.21.0; extra == "all"
Requires-Dist: black>=22.0.0; extra == "all"
Requires-Dist: flake8>=4.0.0; extra == "all"
Requires-Dist: mypy>=0.991; extra == "all"
Requires-Dist: kubernetes>=24.0.0; extra == "all"
Requires-Dist: django>=4.0.0; extra == "all"
Requires-Dist: django-rest-framework>=3.14.0; extra == "all"
Dynamic: author
Dynamic: home-page
Dynamic: license-file
Dynamic: requires-python
